fibrous_python/__init__.py
fibrous_python/core.py
fibrous_python/exceptions.py
fibrous_python/models/__init__.py
fibrous_python/models/enums.py
fibrous_python/models/erc20ABI.py
fibrous_python/models/fibrousRouterABI.py
fibrous_python/models/route.py
fibrous_python/models/token.py
fibrous_python/utils/__init__.py
fibrous_python/utils/approve_helper.py
fibrous_python/utils/route_helper.py
fibrous_python-0.1.0.dist-info/LICENSE
fibrous_python-0.1.0.dist-info/METADATA
fibrous_python-0.1.0.dist-info/WHEEL
fibrous_python-0.1.0.dist-info/entry_points.txt
fibrous_python-0.1.0.dist-info/top_level.txt
fibrous_python-0.1.0.dist-info/RECORD
